twitchirc_drgreengiant/__init__.py
twitchirc_drgreengiant/bufferedsocket.py
twitchirc_drgreengiant/offlineirc.py
twitchirc_drgreengiant/twitchirc.py
twitchirc_drgreengiant-2.1.0.dist-info/LICENSE
twitchirc_drgreengiant-2.1.0.dist-info/METADATA
twitchirc_drgreengiant-2.1.0.dist-info/WHEEL
twitchirc_drgreengiant-2.1.0.dist-info/top_level.txt
twitchirc_drgreengiant-2.1.0.dist-info/RECORD
